osuca/__init__.py
osuca/api.py
osuca/arity.py
osuca/combination.py
osuca/db.py
osuca/summary.py
osuca/term.py
osuca/model/JSONAdapter.py
osuca/model/analytics.py
osuca/model/arity.py
osuca/model/course.py
osuca/model/quarter.py
osuca/static/__init__.py
osuca/static/reviews.csv
osuca/static/site.css
osuca/static/js/chartjs/chart.esm.js
osuca/static/js/chartjs/chart.js
osuca/static/js/chartjs/chart.min.js
osuca/static/js/chartjs/helpers.esm.js
osuca/static/js/chartjs/chunks/helpers.segment.js
osuca/templates/arity.html
osuca/templates/base.html
osuca/templates/combination.html
osuca/templates/summary.html
osuca/templates/term.html
osuca-2.2.2.dist-info/METADATA
osuca-2.2.2.dist-info/WHEEL
osuca-2.2.2.dist-info/licenses/LICENSE
osuca-2.2.2.dist-info/RECORD
