Metadata-Version: 2.1
Name: osuca
Version: 2.2.2
Summary: OSU Course Analytics
Project-URL: Homepage, https://github.com/ozbakan/osuca
Author-email: Tolga Ozbakan <tolga@ozbakan.com>
License: MIT License
Classifier: License :: OSI Approved :: MIT License
Classifier: Operating System :: OS Independent
Classifier: Programming Language :: Python :: 3
Requires-Python: >=3.7
Requires-Dist: flask
Requires-Dist: flask-cors
Requires-Dist: flask-restful
Requires-Dist: requests
